{"URL": "https://www.greenimagetech.com/shop/outdoor-lighting/led-wall-lights/gh-rc1/", "product_info": [{"product_title": "GH-RC1", "product_category": "LED Wall Lights", "product_details_list": ["Die-cast grey powder coated aluminium", "PC cover", "Housing color choice of: jet-black, white and grey", "Bottom directional lighting"]}], "specifications": [{"Model": "GH-RC1-10", "Lumen Output": "1170 lm", "Power": "10W", "Color Temperature (CCT)": "3000K, 4000K", "Input Voltage": "120/240V AC", "Dimension": "112 x 146 mm, Ø 80", "Beam Angle": "15°, 24°, 38°, 60°", "Operating Temperature": "-20°C~40°C", "Certification": "cETLus, RoHS", "IP Rating": "IP65", "Warranty": "5 Years"}, {"Model": "GH-RC1-18", "Lumen Output": "1432 lm", "Power": "18W", "Color Temperature (CCT)": "3000K, 4000K", "Input Voltage": "120/240V AC", "Dimension": "140 x 195.5 mm, Ø 100", "Beam Angle": "12°, 22°, 38°, 55°", "Operating Temperature": "-20°C~40°C", "Certification": "cETLus, RoHS", "IP Rating": "IP65", "Warranty": "5 Years"}, {"Model": "GH-RC1-25", "Lumen Output": "2412 lm", "Power": "25W", "Color Temperature (CCT)": "3000K, 4000K", "Input Voltage": "120/240V AC", "Dimension": "183 x 244 mm, Ø 130", "Beam Angle": "10°, 22°, 38°", "Operating Temperature": "-20°C~40°C", "Certification": "cETLus, RoHS", "IP Rating": "IP65", "Warranty": "5 Years"}, {"Model": "GH-RC1-40", "Lumen Output": "3808 lm", "Power": "40W", "Color Temperature (CCT)": "3000K, 4000K", "Input Voltage": "120/240V AC", "Dimension": "221.7 x 284 mm, Ø 160", "Beam Angle": "12°, 25°, 38°", "Operating Temperature": "-20°C~40°C", "Certification": "cETLus, RoHS", "IP Rating": "IP65", "Warranty": "5 Years"}]}