{"URL": "https://www.greenimagetech.com/shop/indoor-lighting/led-downlights/gd-uts/", "product_info": [{"product_title": "GD-UTS", "product_category": "LED Downlights", "product_details_list": ["Surface Mount Fixture", "Die-cast aluminum housings are available in a variety", "High efficiency and quality colour rendering", "Optional pendant adapter to convert to a hanging fixture"]}], "specifications": [{"Model": "GD-UTS-5", "Lumen Output": "1125 lm", "Power Consumption": "14 W", "Colour Temperature": "3000K", "CRI": "Ra>90", "Dimension": "4.5″ x 4.5″ x 0.75″", "Certification": "CE, cETLus", "Warranty": "5 Years"}, {"Model": "GD-UTS-7", "Lumen Output": "1350 lm", "Power Consumption": "15 W", "Colour Temperature": "3000K", "CRI": "Ra>90", "Dimension": "6.5″ x 6.5″ x 0.75″", "Certification": "CE, cETLus", "Warranty": "5 Years"}]}