{"URL": "https://www.greenimagetech.com/shop/outdoor-lighting/led-inground-lights/gg-04lpwl5/", "product_info": [{"product_title": "GG-04LPWL5", "product_category": "LED Inground Lights", "product_details_list": ["Wall Light", "Die cast aluminum housing", "Perfect for pathways or stairs", "Over 50,000 hours of life", "Grey powder coated"]}], "specifications": [{"Model": "GG-04LPWL5", "Lumen Output": "236 lm", "Power": "4W", "Color": "3000K, 4000K", "Input Voltage": "120V AC", "Dimensions": "220 x 70 x 37 mm", "Operating Temperature": "-20°C~40°C", "IP Rating": "IP65", "Certification": "cETLus", "Warranty": "5 Years"}]}